llmprototyping/__init__.py
llmprototyping/cache.py
llmprototyping/embeddings_interface.py
llmprototyping/embeddings_ollama.py
llmprototyping/embeddings_openai.py
llmprototyping/error.py
llmprototyping/factory.py
llmprototyping/llm_anthropic.py
llmprototyping/llm_em_ollama.py
llmprototyping/llm_groq.py
llmprototyping/llm_interface.py
llmprototyping/llm_openai.py
llmprototyping/serializable.py
llmprototyping/templates.py
llmprototyping/vectordb.py
llmprototyping-0.1.0.dev6.dist-info/LICENSE
llmprototyping-0.1.0.dev6.dist-info/METADATA
llmprototyping-0.1.0.dev6.dist-info/WHEEL
llmprototyping-0.1.0.dev6.dist-info/top_level.txt
llmprototyping-0.1.0.dev6.dist-info/RECORD
