Metadata-Version: 2.1
Name: llmprototyping
Version: 0.1.0.dev6
Summary: A lightweight set of tools to use several llm and embeddings apis
Home-page: https://github.com/alejandrolc/llmprototyping
Author: Alejandro López Correa
Keywords: llm,rag,openai,groq,ollama,anthropic
Classifier: Development Status :: 2 - Pre-Alpha
Classifier: Intended Audience :: Developers
Classifier: Topic :: Scientific/Engineering :: Artificial Intelligence
Classifier: License :: OSI Approved :: Apache Software License
Requires-Python: >=3.9, <4
License-File: LICENSE
Requires-Dist: groq
Requires-Dist: openai
Requires-Dist: tiktoken
Requires-Dist: packaging
Requires-Dist: faiss-cpu
Requires-Dist: ollama
Requires-Dist: anthropic
